README
setup.py
yadayada/__init__.py
yadayada/countries.py
yadayada/db.py
yadayada/generate_countries.py
yadayada/managers.py
yadayada/models.py
yadayada/views.py
yadayada.egg-info/PKG-INFO
yadayada.egg-info/SOURCES.txt
yadayada.egg-info/dependency_links.txt
yadayada.egg-info/requires.txt
yadayada.egg-info/top_level.txt
yadayada/importers/__init__.py
yadayada/importers/image.py
yadayada/importers/xml.py
yadayada/test/__init__.py
yadayada/test/user.py
yadayada/tests/__init__.py
yadayada/tests/test_models.py
yadayada/utils/__init__.py
yadayada/utils/functional.py
yadayada/utils/http.py
