Metadata-Version: 1.0
Name: yadayada
Version: 0.8.0
Summary: Common Django utilities
Home-page: UNKNOWN
Author: Ask Solem
Author-email: askh@opera.com
License: UNKNOWN
Platform: UNKNOWN
Classifier: Development Status :: 3 - Alpha
Classifier: Framework :: Django
Classifier: Operating System :: OS Independent
Classifier: Programming Language :: Python
